degreesConversion/__init__.py
degreesConversion/converter.py
degreesconversion-0.0.2.dist-info/METADATA
degreesconversion-0.0.2.dist-info/WHEEL
degreesconversion-0.0.2.dist-info/licenses/LICENSE
degreesconversion-0.0.2.dist-info/RECORD
