Metadata-Version: 2.1
Name: degreesConversion
Version: 0.0.2
Summary: A simple temperature conversion package
Project-URL: Homepage, https://github.com/nicola-lamaddalena/Degrees-converter
Project-URL: Bug Tracker, https://github.com/nicola-lamaddalena/Degrees-converter/issues
Author-email: Nicola Lamaddalena <lamaddalena.nicola1@gmail.com>
License-File: LICENSE
Classifier: License :: OSI Approved :: MIT License
Classifier: Operating System :: OS Independent
Classifier: Programming Language :: Python :: 3
Requires-Python: >=3.7
